NotificationList/__init__.py
NotificationList/main.py
notificationlist-0.1.4.dist-info/licenses/LICENSE
notificationlist-0.1.4.dist-info/METADATA
notificationlist-0.1.4.dist-info/WHEEL
notificationlist-0.1.4.dist-info/top_level.txt
notificationlist-0.1.4.dist-info/RECORD
