Metadata-Version: 2.4
Name: NotificationList
Version: 0.1.4
Summary: A Python package for consolidating breach response notification lists efficiently.
Author: Ranjeet Aloriya
Author-email: ranjeet.aloriya@gmail.com
License: MIT
Classifier: Programming Language :: Python :: 3
Classifier: License :: OSI Approved :: MIT License
Classifier: Operating System :: OS Independent
Requires-Python: >=3.6
License-File: LICENSE
Requires-Dist: pandas
Requires-Dist: polars
Dynamic: author
Dynamic: author-email
Dynamic: classifier
Dynamic: description
Dynamic: description-content-type
Dynamic: license
Dynamic: license-file
Dynamic: requires-dist
Dynamic: requires-python
Dynamic: summary
